thothai_cli/__init__.py
thothai_cli/cli.py
thothai_cli/commands/__init__.py
thothai_cli/commands/config.py
thothai_cli/commands/data.py
thothai_cli/commands/deploy.py
thothai_cli/commands/init.py
thothai_cli/commands/prune.py
thothai_cli/commands/swarm.py
thothai_cli/core/__init__.py
thothai_cli/core/config_manager.py
thothai_cli/core/docker_manager.py
thothai_cli/templates/__init__.py
thothai_cli/templates/config.yml
thothai_cli/templates/docker-compose.yml
thothai_cli/templates/docker-stack.yml
thothai_cli/templates/swarm_config.env
thothai_cli/templates/data/dev_databases/california_schools/california_schools.sqlite
thothai_cli/templates/data/dev_databases/california_schools/database_description/frpm.csv
thothai_cli/templates/data/dev_databases/california_schools/database_description/satscores.csv
thothai_cli/templates/data/dev_databases/california_schools/database_description/schools.csv
thothai_cli/templates/data/dev_databases/california_schools/preprocessed/california_schools_lsh.pkl
thothai_cli/templates/data/dev_databases/california_schools/preprocessed/california_schools_minhashes.pkl
thothai_cli/templates/data/dev_databases/california_schools/preprocessed/california_schools_unique_values.pkl
thothai_cli/templates/setup_csv/agent.csv
thothai_cli/templates/setup_csv/aimodel.csv
thothai_cli/templates/setup_csv/basicaimodel.csv
thothai_cli/templates/setup_csv/groupprofile.csv
thothai_cli/templates/setup_csv/groups.csv
thothai_cli/templates/setup_csv/setting.csv
thothai_cli/templates/setup_csv/users.csv
thothai_cli/templates/setup_csv/workspace.csv
thothai_cli/templates/setup_csv/docker/california_schools_columns.csv
thothai_cli/templates/setup_csv/docker/california_schools_relationships.csv
thothai_cli/templates/setup_csv/docker/california_schools_tables.csv
thothai_cli/templates/setup_csv/docker/selected_dbs.csv
thothai_cli/templates/setup_csv/docker/vectordb.csv
thothai_cli/templates/setup_csv/local/california_schools_columns.csv
thothai_cli-1.3.8.dist-info/METADATA
thothai_cli-1.3.8.dist-info/WHEEL
thothai_cli-1.3.8.dist-info/entry_points.txt
thothai_cli-1.3.8.dist-info/licenses/LICENSE.md
thothai_cli-1.3.8.dist-info/RECORD
