Metadata-Version: 2.4
Name: thothai-cli
Version: 1.3.8
Summary: ThothAI unified CLI - Deploy and manage ThothAI without cloning the repository
Project-URL: Homepage, https://github.com/mptyl/ThothAI
Project-URL: Repository, https://github.com/mptyl/ThothAI
Project-URL: Documentation, https://thoth-ai.readthedocs.io
Author-email: Marco Pancotti <mp@tylconsulting.it>
License: 
License-File: LICENSE.md
Keywords: ai,deployment,docker,sql,text-to-sql,thothai
Classifier: Development Status :: 4 - Beta
Classifier: Environment :: Console
Classifier: Intended Audience :: Developers
Classifier: Intended Audience :: System Administrators
Classifier: License :: OSI Approved :: Apache Software License
Classifier: Operating System :: OS Independent
Classifier: Programming Language :: Python :: 3
Classifier: Programming Language :: Python :: 3.9
Classifier: Programming Language :: Python :: 3.10
Classifier: Programming Language :: Python :: 3.11
Classifier: Programming Language :: Python :: 3.12
Classifier: Programming Language :: Python :: 3.13
Classifier: Topic :: Database
Classifier: Topic :: Software Development :: Code Generators
Classifier: Topic :: System :: Installation/Setup
Requires-Python: >=3.9
Requires-Dist: click>=8.0
Requires-Dist: docker>=7.0
Requires-Dist: pyyaml>=6.0
Requires-Dist: rich>=13.0
Requires-Dist: thothai-cli-core
